xin/__init__.py
xin/bing.py
xin/cli.py
xin/image.py
xin/net.py
xin/os.py
xin-2019.9.19.dist-info/LICENSE
xin-2019.9.19.dist-info/METADATA
xin-2019.9.19.dist-info/WHEEL
xin-2019.9.19.dist-info/entry_points.txt
xin-2019.9.19.dist-info/top_level.txt
xin-2019.9.19.dist-info/RECORD
